hotmail_flask_mailer/__init__.py
hotmail_flask_mailer/app.py
hotmail_flask_mailer-0.1.0.dist-info/METADATA
hotmail_flask_mailer-0.1.0.dist-info/WHEEL
hotmail_flask_mailer-0.1.0.dist-info/entry_points.txt
hotmail_flask_mailer-0.1.0.dist-info/top_level.txt
hotmail_flask_mailer-0.1.0.dist-info/RECORD
